flask_protector_app/__init__.py
flask_protector_app/config.py
flask_protector_app/example.py
flask_protector_app/static/style.css
flask_protector_app/templates/base.html
flask_protector_app/templates/login.html
flask_protector_app/templates/redirect.html
flask_protector_app-1.1.0.dist-info/METADATA
flask_protector_app-1.1.0.dist-info/WHEEL
flask_protector_app-1.1.0.dist-info/top_level.txt
flask_protector_app-1.1.0.dist-info/RECORD
